fractal_feature_explorer/__init__.py
fractal_feature_explorer/authentication.py
fractal_feature_explorer/cli.py
fractal_feature_explorer/config.py
fractal_feature_explorer/main.py
fractal_feature_explorer/pages/export_page.py
fractal_feature_explorer/pages/info.py
fractal_feature_explorer/pages/explore_page/__init__.py
fractal_feature_explorer/pages/explore_page/_heat_map_plot.py
fractal_feature_explorer/pages/explore_page/_scatter_plot.py
fractal_feature_explorer/pages/explore_page/explore_page.py
fractal_feature_explorer/pages/filters_page/__init__.py
fractal_feature_explorer/pages/filters_page/_column_filter.py
fractal_feature_explorer/pages/filters_page/_common.py
fractal_feature_explorer/pages/filters_page/_histogram_filter.py
fractal_feature_explorer/pages/filters_page/_scatter_filter.py
fractal_feature_explorer/pages/filters_page/filters_page.py
fractal_feature_explorer/pages/setup_page/__init__.py
fractal_feature_explorer/pages/setup_page/_plate_advanced_selection.py
fractal_feature_explorer/pages/setup_page/_plate_mode_setup.py
fractal_feature_explorer/pages/setup_page/_tables_io.py
fractal_feature_explorer/pages/setup_page/_utils.py
fractal_feature_explorer/pages/setup_page/setup_page.py
fractal_feature_explorer/resources/config.toml
fractal_feature_explorer/resources/fractal_favicon.png
fractal_feature_explorer/resources/fractal_logo.png
fractal_feature_explorer/utils/__init__.py
fractal_feature_explorer/utils/common.py
fractal_feature_explorer/utils/file_path_picker.py
fractal_feature_explorer/utils/ngio_io_caches.py
fractal_feature_explorer/utils/st_components.py
fractal_feature_explorer-0.1.13.dist-info/METADATA
fractal_feature_explorer-0.1.13.dist-info/WHEEL
fractal_feature_explorer-0.1.13.dist-info/entry_points.txt
fractal_feature_explorer-0.1.13.dist-info/licenses/LICENSE
fractal_feature_explorer-0.1.13.dist-info/RECORD
